{"clipboardHistory":[{"value":"dot add -u","recorded":"2025-07-09 13:37:58.739800764","filePath":"null","pinned":false},{"value":"dot config --local status.showUntrackedFiles no","recorded":"2025-07-09 13:37:47.135416391","filePath":"null","pinned":false},{"value":"dot status -sb","recorded":"2025-07-09 13:37:27.717524497","filePath":"null","pinned":false},{"value":"alias dot='git --git-dir=$HOME/.dotfiles --work-tree=$HOME'","recorded":"2025-07-09 13:37:17.930026016","filePath":"null","pinned":false},{"value":"https://github.com/almostbinary","recorded":"2025-07-09 13:31:16.092450509","filePath":"null","pinned":false},{"value":"/home/dex/Downloads/sukuna-red-5120x2880-16933.png","recorded":"2025-07-09 13:25:10.444254324","filePath":"null","pinned":false},{"value":"/home/dex/Downloads/dark-aesthetic-city-5120x2880-22091.png","recorded":"2025-07-09 12:50:22.560346995","filePath":"null","pinned":false},{"value":"📷 32984-842058804.png","recorded":"2025-07-09 12:42:17.849434286","filePath":"/home/dex/.config/clipse/tmp_files/32984-842058804.png","pinned":false},{"value":"bind = SUPER CTRL, left, movecurrentworkspacetomonitor, l","recorded":"2025-07-09 12:40:34.334672370","filePath":"null","pinned":false},{"value":"hyprctl dispatch movecurrentworkspacetomonitor r","recorded":"2025-07-09 12:36:17.336637158","filePath":"null","pinned":false},{"value":"📷 309005-262680785.png","recorded":"2025-07-09 12:17:33.347443701","filePath":"/home/dex/.config/clipse/tmp_files/309005-262680785.png","pinned":false},{"value":"📷 312001-112493240.png","recorded":"2025-07-09 11:06:01.198958825","filePath":"/home/dex/.config/clipse/tmp_files/312001-112493240.png","pinned":false},{"value":"📷 111304-726909221.png","recorded":"2025-07-09 11:01:20.769024443","filePath":"/home/dex/.config/clipse/tmp_files/111304-726909221.png","pinned":false},{"value":"📷 54601-413844047.png","recorded":"2025-07-09 11:00:12.431541630","filePath":"/home/dex/.config/clipse/tmp_files/54601-413844047.png","pinned":false},{"value":"yay -S zen-browser-bin","recorded":"2025-07-09 10:59:57.672334658","filePath":"null","pinned":false},{"value":"rm -rf ~/.mozilla","recorded":"2025-07-09 10:59:46.317012554","filePath":"null","pinned":false},{"value":"rm -rf ~/.zen","recorded":"2025-07-09 10:59:16.776756574","filePath":"null","pinned":false},{"value":"pacman -Qo /usr/.zen /usr/bin/zen 2\u003e/dev/null","recorded":"2025-07-09 10:54:52.750151184","filePath":"null","pinned":false},{"value":"📷 138772-203680903.png","recorded":"2025-07-09 10:51:40.236282218","filePath":"/home/dex/.config/clipse/tmp_files/138772-203680903.png","pinned":false},{"value":"/usr/.zen","recorded":"2025-07-09 10:51:21.884795116","filePath":"null","pinned":false},{"value":"# make sure you really have a duplicate\nls -l /usr/.zen  /usr/bin/zen 2\u003e/dev/null\n\n# if they exist and are NOT part of a package, delete them\nsudo rm -rf /usr/.zen /usr/bin/zen\n","recorded":"2025-07-09 10:49:46.372357890","filePath":"null","pinned":false},{"value":"ls -l /usr/.zen  /usr/bin/zen 2\u003e/dev/null","recorded":"2025-07-09 10:46:54.076214511","filePath":"null","pinned":false},{"value":"i seem to also have mozilla folder. Dont know why","recorded":"2025-07-09 10:41:54.668483329","filePath":"null","pinned":false},{"value":"📷 15857-910944061.png","recorded":"2025-07-09 10:41:00.915090460","filePath":"/home/dex/.config/clipse/tmp_files/15857-910944061.png","pinned":false},{"value":"📷 49356-559066556.png","recorded":"2025-07-09 10:28:34.573059157","filePath":"/home/dex/.config/clipse/tmp_files/49356-559066556.png","pinned":false},{"value":"📷 70357-033592728.png","recorded":"2025-07-09 10:26:18.058286373","filePath":"/home/dex/.config/clipse/tmp_files/70357-033592728.png","pinned":false},{"value":"hyprctl activewindow","recorded":"2025-07-09 10:20:46.521830297","filePath":"null","pinned":false},{"value":"https://app.excalidraw.com/s/7td2ATQ4yXJ/4xYy2kKC9jq","recorded":"2025-07-09 10:13:19.449997675","filePath":"null","pinned":false},{"value":"yay -Rns zen-browser-bin","recorded":"2025-07-09 10:03:23.277771294","filePath":"null","pinned":false},{"value":" ","recorded":"2025-07-09 10:03:09.379847334","filePath":"null","pinned":false},{"value":"git clone https://aur.archlinux.org/zen-browser-bin.git","recorded":"2025-07-09 01:44:11.354873939","filePath":"null","pinned":false},{"value":"https://zen-browser.app/download/","recorded":"2025-07-09 01:42:33.860029986","filePath":"null","pinned":false},{"value":"📷 222686-560881761.png","recorded":"2025-07-09 01:18:00.642844532","filePath":"/home/dex/.config/clipse/tmp_files/222686-560881761.png","pinned":false},{"value":"window#waybar{\n  background: transparent","recorded":"2025-07-09 01:17:19.953348043","filePath":"null","pinned":false},{"value":"\"https://app.excalidraw.com/s/7td2ATQ4yXJ/4xYy2kKC9jq\"","recorded":"2025-07-09 01:06:17.443156815","filePath":"null","pinned":false},{"value":"Exec=chromium --new-window \\\n     --ozone-platform=wayland \\  # Use native Wayland backend (Chromium flag)\n     --app=\"https://youtube.com\" # PWA-like frameless window\n     --name=\"YouTube\"            # Window title (WM_NAME)\n     --class=\"YouTube\"  ","recorded":"2025-07-09 01:04:13.618122190","filePath":"null","pinned":false},{"value":"[Desktop Entry]\nVersion=1.0\nName=Emacs\nComment=Doom Emacs\nExec=emacs\nTerminal=false\nType=Application\nIcon=/home/dex/.local/share/applications/icons/doom.png\nStartupNotify=true\n","recorded":"2025-07-09 00:55:02.251116829","filePath":"null","pinned":false},{"value":"=chromium --new-window --ozone-platform=wayland --app=\"https://youtube.com/\" --name=\"YouTube\" --class=\"YouTube\"\n","recorded":"2025-07-09 00:53:45.354167240","filePath":"null","pinned":false},{"value":"[Desktop Entry]\nName=Emacs\nGenericName=Text Editor\nComment=GNU Emacs (Doom flavour)\nExec=emacsclient -c -a \"\"         # or plain “emacs” if you don’t use the server\nIcon=emacs                        # uses whatever “emacs” icon your theme ships\nType=Application\nCategories=Development;TextEditor;\nTerminal=false\nStartupNotify=true","recorded":"2025-07-09 00:53:01.376600003","filePath":"null","pinned":false},{"value":"[Desktop Entry]\nName=Emacs\nGenericName=Text Editor\nComment=GNU Emacs (Doom flavour)\nExec=emacsclient -c -a \"\"         # or plain “emacs” if you don’t use the server\nIcon=emacs                        # uses whatever “emacs” icon your theme ships\nType=Application\nCategories=Development;TextEditor;\nTerminal=false\nStartupNotify=true\n","recorded":"2025-07-09 00:52:47.550006588","filePath":"null","pinned":false},{"value":"[Desktop Entry]\nVersion=1.0\nName=YouTube\nComment=YouTube\nExec=chromium --new-window --ozone-platform=wayland --app=\"https://youtube.com/\" --name=\"YouTube\" --class=\"YouTube\"\nTerminal=false\nType=Application\nIcon=/home/dex/.local/share/applications/icons/YouTube.png\nStartupNotify=true","recorded":"2025-07-09 00:42:53.029449502","filePath":"null","pinned":false},{"value":"#","recorded":"2025-07-07 21:43:06.438781990","filePath":"null","pinned":false},{"value":"cd ~/.local/share/omarchy","recorded":"2025-07-07 20:30:35.821216360","filePath":"null","pinned":false},{"value":"📷 22163-729174345.png","recorded":"2025-07-07 20:21:17.736545788","filePath":"/home/dex/.config/clipse/tmp_files/22163-729174345.png","pinned":false},{"value":"849366","recorded":"2025-07-05 14:05:52.319512667","filePath":"null","pinned":false},{"value":"958784","recorded":"2025-07-05 13:48:44.615241701","filePath":"null","pinned":false},{"value":"📷 174667-347007441.png","recorded":"2025-07-05 12:46:53.421567960","filePath":"/home/dex/.config/clipse/tmp_files/174667-347007441.png","pinned":false},{"value":"📷 18158-108914021.png","recorded":"2025-07-05 12:24:03.113912232","filePath":"/home/dex/.config/clipse/tmp_files/18158-108914021.png","pinned":false},{"value":"\"","recorded":"2025-07-04 16:14:52.321308399","filePath":"null","pinned":false},{"value":"https://www.icloud.com/notes","recorded":"2025-07-04 16:14:44.161207283","filePath":"null","pinned":false},{"value":"=","recorded":"2025-07-04 16:14:38.602610059","filePath":"null","pinned":false},{"value":"c","recorded":"2025-07-04 16:14:35.430959041","filePath":"null","pinned":false},{"value":"j","recorded":"2025-07-04 16:14:35.092001988","filePath":"null","pinned":false},{"value":"Q","recorded":"2025-07-04 16:14:34.689985460","filePath":"null","pinned":false},{"value":"d","recorded":"2025-07-04 16:14:34.362072309","filePath":"null","pinned":false},{"value":"M","recorded":"2025-07-04 16:14:34.048594116","filePath":"null","pinned":false},{"value":"x","recorded":"2025-07-04 16:14:33.907717362","filePath":"null","pinned":false},{"value":"Y","recorded":"2025-07-04 16:14:33.770664170","filePath":"null","pinned":false},{"value":"0","recorded":"2025-07-04 16:14:33.612367858","filePath":"null","pinned":false},{"value":"B","recorded":"2025-07-04 16:14:33.298738547","filePath":"null","pinned":false},{"value":"F","recorded":"2025-07-04 16:14:33.119408101","filePath":"null","pinned":false},{"value":"T","recorded":"2025-07-04 16:14:32.931436024","filePath":"null","pinned":false},{"value":"O","recorded":"2025-07-04 16:14:32.892251614","filePath":"null","pinned":false},{"value":"y","recorded":"2025-07-04 16:14:32.847370141","filePath":"null","pinned":false},{"value":"i","recorded":"2025-07-04 16:14:32.767916521","filePath":"null","pinned":false},{"value":"N","recorded":"2025-07-04 16:14:32.731784651","filePath":"null","pinned":false},{"value":"3","recorded":"2025-07-04 16:14:32.691695504","filePath":"null","pinned":false},{"value":"t","recorded":"2025-07-04 16:14:31.736917915","filePath":"null","pinned":false},{"value":"E","recorded":"2025-07-04 16:14:31.692731017","filePath":"null","pinned":false},{"value":"z","recorded":"2025-07-04 16:14:31.572485885","filePath":"null","pinned":false},{"value":"L","recorded":"2025-07-04 16:14:31.455964403","filePath":"null","pinned":false},{"value":"1","recorded":"2025-07-04 16:14:06.209164464","filePath":"null","pinned":false},{"value":"5","recorded":"2025-07-04 16:14:06.089998367","filePath":"null","pinned":false},{"value":"D","recorded":"2025-07-04 16:14:05.930647510","filePath":"null","pinned":false},{"value":"p","recorded":"2025-07-04 16:14:05.726161082","filePath":"null","pinned":false},{"value":"V","recorded":"2025-07-04 16:14:05.567758061","filePath":"null","pinned":false},{"value":"2","recorded":"2025-07-04 16:14:05.527916899","filePath":"null","pinned":false},{"value":"R","recorded":"2025-07-04 16:14:05.406519696","filePath":"null","pinned":false},{"value":"n","recorded":"2025-07-04 16:14:05.372443541","filePath":"null","pinned":false},{"value":"b","recorded":"2025-07-04 16:14:05.326664778","filePath":"null","pinned":false},{"value":"l","recorded":"2025-07-04 16:14:05.291168431","filePath":"null","pinned":false},{"value":"J","recorded":"2025-07-04 16:14:05.246514663","filePath":"null","pinned":false},{"value":"m","recorded":"2025-07-04 16:14:05.046197617","filePath":"null","pinned":false},{"value":"6","recorded":"2025-07-04 16:14:04.967835821","filePath":"null","pinned":false},{"value":"X","recorded":"2025-07-04 16:14:04.890473191","filePath":"null","pinned":false},{"value":"Z","recorded":"2025-07-04 16:14:04.850467033","filePath":"null","pinned":false},{"value":"9","recorded":"2025-07-04 16:14:04.767264823","filePath":"null","pinned":false},{"value":"o","recorded":"2025-07-04 16:14:04.611018492","filePath":"null","pinned":false},{"value":"H","recorded":"2025-07-04 16:14:04.250312144","filePath":"null","pinned":false},{"value":"U","recorded":"2025-07-04 16:14:04.211280265","filePath":"null","pinned":false},{"value":"/","recorded":"2025-07-04 16:14:04.165925522","filePath":"null","pinned":false},{"value":"e","recorded":"2025-07-04 16:14:04.130292115","filePath":"null","pinned":false},{"value":"s","recorded":"2025-07-04 16:14:03.930467415","filePath":"null","pinned":false},{"value":".","recorded":"2025-07-04 16:14:03.570999687","filePath":"null","pinned":false},{"value":"u","recorded":"2025-07-04 16:14:03.486019165","filePath":"null","pinned":false},{"value":"w","recorded":"2025-07-04 16:14:03.246179315","filePath":"null","pinned":false},{"value":":","recorded":"2025-07-04 16:14:03.049981291","filePath":"null","pinned":false},{"value":"h","recorded":"2025-07-04 16:14:02.309257812","filePath":"null","pinned":false},{"value":"https://www.icloud.com/notes/note/UHJpdmF0ZTo6Tm90ZXM6OmN1cnJlbnRVc2VyOjpEQzFDNzM5My1FN0FELTQzM0EtOTM3Ni0yOTFBM0YxMjdEQjc=","recorded":"2025-07-04 16:12:22.856074513","filePath":"null","pinned":false},{"value":"https://discord.com/channels/@me","recorded":"2025-07-03 18:31:18.294342022","filePath":"null","pinned":false}]}